{
  "phase": "ARP_Prototype_Repo_Compliance_Audit",
  "status": "COMPLETE",
  "result": "NON_COMPLIANT_FOR_PROJECTION",
  "axioms_required": "NONE",
  "new_contextual_embeddings_required": "NONE",
  "application_functions_required": "YES",
  "notes": [
    "All prototypes are heuristic-only and structurally compatible",
    "No new axioms are required",
    "No new IEL domains are required",
    "Embedded logic must be extracted into governed application functions",
    "Proof projection is blocked until application-function refactor"
  ]
}