{
  "artifact": "ARP_Reconstructed_Modules",
  "version": "V1.0.0",
  "location": "DEV_RESOURCES/IN_DEV_BLUEPRINTS/INTEGRATIONS/V1.0.0",
  "status": "ACCEPTED",
  "posture": "DESIGN_ONLY",
  "logic_present": false,
  "proof_projection": "BLOCKED",
  "autonomy": "DENIED",
  "basis": [
    "ARP_PROTOTYPE_RECONSTRUCTION_SPEC.md",
    "ARP_V1_RECONSTRUCTED_COMPLIANCE_AUDIT.json",
    "ARP_V1_RECONSTRUCTED_COMPLIANCE_SUMMARY.md"
  ],
  "notes": "V1.0.0 accepted as integration-ready design baseline. Any future changes require new version and audit."
}
